carag/__init__.py
carag/llm_pipeline.py
carag/rag_pipeline.py
carag/version.py
carag-1.0.8.dist-info/licenses/LICENSE.txt
carag-1.0.8.dist-info/METADATA
carag-1.0.8.dist-info/WHEEL
carag-1.0.8.dist-info/top_level.txt
carag-1.0.8.dist-info/RECORD
