Metadata-Version: 2.4
Name: carag
Version: 1.0.8
Summary: An efficient python library for building AI applications using the Retrieval-Augmented Generation (RAG) pipeline.
Home-page: https://github.com/rizwandel/Build-Standard-RAG-with-Qdrant
Author: Mohamed Rizwan
Author-email: Mohamed Rizwan <rizdelhi@gmail.com>
Keywords: Semantic search,RAG,Mistral AI,Retrieval,Qdrant
Classifier: Development Status :: 3 - Alpha
Classifier: Intended Audience :: Developers
Classifier: Topic :: Scientific/Engineering :: Artificial Intelligence
Classifier: License :: OSI Approved :: GNU General Public License v3 (GPLv3)
Classifier: Programming Language :: Python :: 3
Classifier: Operating System :: OS Independent
Requires-Python: >=3.9
License-File: LICENSE.txt
Requires-Dist: mistralai==1.6.0
Requires-Dist: PyMuPDF==1.25.3
Requires-Dist: fastembed==0.6.0
Requires-Dist: qdrant-client==1.10.0
Requires-Dist: python-dotenv==1.1.0
Requires-Dist: ipywidgets==8.1.6
Dynamic: author
Dynamic: home-page
Dynamic: license-file
Dynamic: requires-python
